keystamp_common/__init__.py
keystamp_common/config.py
keystamp_common/signing.py
keystamp_common/types.py
keystamp_common/versions.py
keystamp_common-0.1.0.dist-info/METADATA
keystamp_common-0.1.0.dist-info/WHEEL
keystamp_common-0.1.0.dist-info/top_level.txt
keystamp_common-0.1.0.dist-info/RECORD
